README.md
README.txt
setup.py
freessl/__init__.py
freessl/__main__.py
freessl/freessl.py
freessl/helpers.py
freessl/utils.py
freessl.egg-info/PKG-INFO
freessl.egg-info/SOURCES.txt
freessl.egg-info/dependency_links.txt
freessl.egg-info/entry_points.txt
freessl.egg-info/requires.txt
freessl.egg-info/top_level.txt